aag/__init__.py
aag/cli.py
aag/commands.py
aag/server.py
aag/settings.py
aag/weather.py
panoptes_aag-0.0.5.dist-info/LICENSE.txt
panoptes_aag-0.0.5.dist-info/METADATA
panoptes_aag-0.0.5.dist-info/WHEEL
panoptes_aag-0.0.5.dist-info/entry_points.txt
panoptes_aag-0.0.5.dist-info/top_level.txt
panoptes_aag-0.0.5.dist-info/RECORD
