Metadata-Version: 2.1
Name: panoptes-aag
Version: 0.0.5
Summary: Weather service for the Lunatico AAG CloudWatcher.
Home-page: https://github.com/panoptes/aag-weather/
Author: Wilfred Tyler Gee
Author-email: wtylergee@gmail.com
License: MIT
Project-URL: Documentation, https://projectpanoptes.org/
Platform: linux
Classifier: Development Status :: 4 - Beta
Classifier: Programming Language :: Python
Requires-Python: >=3.11
License-File: LICENSE.txt
Requires-Dist: astropy
Requires-Dist: fastapi[all]
Requires-Dist: fastapi-utils
Requires-Dist: httpie
Requires-Dist: pandas
Requires-Dist: pydantic
Requires-Dist: pydantic-settings
Requires-Dist: pyserial >=3.4
Requires-Dist: python-dotenv
Requires-Dist: typer[all]
Requires-Dist: importlib-metadata ; python_version < "3.11"
Provides-Extra: building
Requires-Dist: pyscaffold >=4.3.1 ; extra == 'building'
Requires-Dist: pyscaffoldext-markdown ; extra == 'building'
Requires-Dist: tox ; extra == 'building'
Requires-Dist: twine ; extra == 'building'
Provides-Extra: docs
Requires-Dist: myst-parser ; extra == 'docs'
Requires-Dist: piccolo-theme ; extra == 'docs'
Requires-Dist: pytest-mpl ; extra == 'docs'
Requires-Dist: sphinx ; extra == 'docs'
Provides-Extra: testing
Requires-Dist: setuptools ; extra == 'testing'
Requires-Dist: pytest ; extra == 'testing'
Requires-Dist: pytest-cov ; extra == 'testing'
Requires-Dist: tox ; extra == 'testing'
